llm_fecfile.py
llm_fecfile-0.1.0.dist-info/METADATA
llm_fecfile-0.1.0.dist-info/WHEEL
llm_fecfile-0.1.0.dist-info/entry_points.txt
llm_fecfile-0.1.0.dist-info/top_level.txt
llm_fecfile-0.1.0.dist-info/RECORD
