Metadata-Version: 2.4
Name: llm-fecfile
Version: 0.1.0
Summary: LLM plugin for analyzing FEC campaign finance filings
Author: Assistant
License: MIT
Project-URL: Homepage, https://github.com/user/llm-fecfile
Project-URL: Documentation, https://github.com/user/llm-fecfile#readme
Project-URL: Repository, https://github.com/user/llm-fecfile.git
Project-URL: Bug Tracker, https://github.com/user/llm-fecfile/issues
Classifier: Development Status :: 3 - Alpha
Classifier: Intended Audience :: Developers
Classifier: License :: OSI Approved :: MIT License
Classifier: Programming Language :: Python :: 3
Classifier: Programming Language :: Python :: 3.8
Classifier: Programming Language :: Python :: 3.9
Classifier: Programming Language :: Python :: 3.10
Classifier: Programming Language :: Python :: 3.11
Classifier: Topic :: Software Development :: Libraries :: Python Modules
Classifier: Topic :: Text Processing
Requires-Python: >=3.9
Requires-Dist: fecfile>=0.6.0
Requires-Dist: llm>=0.24
